rot_kbd.py
rot_kbd-2024.4.1.post1.dist-info/LICENSE
rot_kbd-2024.4.1.post1.dist-info/METADATA
rot_kbd-2024.4.1.post1.dist-info/WHEEL
rot_kbd-2024.4.1.post1.dist-info/top_level.txt
rot_kbd-2024.4.1.post1.dist-info/RECORD
