Metadata-Version: 2.1
Name: rot-kbd
Version: 2024.4.1.post1
Summary: A terrible encryption scheme, like rot13 but keyboards
Author-email: Alex Willmer <alex@moreati.org.uk>
Project-URL: Homepage, https://github.com/moreati/rot-kbd
Project-URL: Issues, https://github.com/moreati/rot-kbd/issues
Keywords: dvorak,qwerty
Classifier: Development Status :: 4 - Beta
Classifier: Programming Language :: Python :: 3
Classifier: License :: OSI Approved :: MIT License
Classifier: Operating System :: OS Independent
Requires-Python: >=3.8
License-File: LICENSE
